imgdiff.py
imgdiff-1.8.0.dist-info/LICENSE
imgdiff-1.8.0.dist-info/METADATA
imgdiff-1.8.0.dist-info/WHEEL
imgdiff-1.8.0.dist-info/entry_points.txt
imgdiff-1.8.0.dist-info/top_level.txt
imgdiff-1.8.0.dist-info/RECORD
